chalc/__init__.py
chalc/_utils.py
chalc/chromatic.cpython-313-x86_64-linux-gnu.so
chalc/chromatic.pyi
chalc/chromatic_py.cxx
chalc/filtration.cpython-313-x86_64-linux-gnu.so
chalc/filtration.pyi
chalc/filtration_py.cxx
chalc/plotting.py
chalc/py.typed
chalc/chromatic/chromatic.cxx
chalc/chromatic/chromatic.h
chalc/filtration/filtration.cxx
chalc/filtration/filtration.h
chalc/sixpack/__init__.py
chalc/sixpack/morphisms.py
chalc/sixpack/types.py
chalc-14.2.0.dist-info/METADATA
chalc-14.2.0.dist-info/WHEEL
chalc-14.2.0.dist-info/RECORD
chalc-14.2.0.dist-info/licenses/COPYING
