Metadata-Version: 2.2
Name: chalc
Version: 14.2.0
Summary: Persistent homology of chromatic Delaunay filtrations
Keywords: topological data analysis,TDA,chromatic Delaunay,computational geometry,computational topology,persistent homology
Author-Email: Abhinav Natarajan <natarajan@maths.ox.ac.uk>
License:                     GNU GENERAL PUBLIC LICENSE
Classifier: Development Status :: 3 - Alpha
Classifier: Intended Audience :: Science/Research
Classifier: Topic :: Scientific/Engineering :: Mathematics
Classifier: License :: OSI Approved :: GNU General Public License v3 or later (GPLv3+)
Classifier: Programming Language :: C++
Classifier: Programming Language :: Python :: 3
Classifier: Programming Language :: Python :: Implementation :: CPython
Classifier: Programming Language :: Python :: Implementation :: PyPy
Project-URL: Homepage, https://abhinavnatarajan.github.io/Chalc
Project-URL: Documentation, https://abhinavnatarajan.github.io/Chalc
Project-URL: Repository, https://github.com/abhinavnatarajan/Chalc.git
Requires-Python: >=3.13
Requires-Dist: numpy~=2.0
Requires-Dist: phimaker~=0.3.0
Requires-Dist: pandas~=2.2
Requires-Dist: matplotlib~=3.9
Requires-Dist: h5py~=3.12
